pennprov/__init__.py
pennprov/api_client.py
pennprov/configuration.py
pennprov/rest.py
pennprov/api/__init__.py
pennprov/api/authentication_api.py
pennprov/api/decorators.py
pennprov/api/permission_api.py
pennprov/api/prov_api_test.py
pennprov/api/prov_dm_api.py
pennprov/api/provenance_api.py
pennprov/cache/__init__.py
pennprov/cache/graph.py
pennprov/connection/__init__.py
pennprov/connection/mprov_connection.py
pennprov/connection/mprov_connection_cache.py
pennprov/metadata/__init__.py
pennprov/metadata/stream_metadata.py
pennprov/models/__init__.py
pennprov/models/attribute.py
pennprov/models/boolean_attribute.py
pennprov/models/boolean_field_model.py
pennprov/models/double_attribute.py
pennprov/models/double_field_model.py
pennprov/models/field_model.py
pennprov/models/group_details.py
pennprov/models/id_model.py
pennprov/models/int_attribute.py
pennprov/models/integer_field_model.py
pennprov/models/link_info.py
pennprov/models/link_instance.py
pennprov/models/long_attribute.py
pennprov/models/long_field_model.py
pennprov/models/multi_field_model.py
pennprov/models/node_info.py
pennprov/models/node_instance.py
pennprov/models/node_model.py
pennprov/models/org_details.py
pennprov/models/prov_edge_model.py
pennprov/models/prov_edge_set_model.py
pennprov/models/prov_expression_model.py
pennprov/models/prov_location_model.py
pennprov/models/prov_node_map_model.py
pennprov/models/prov_specifier_field_model.py
pennprov/models/prov_specifier_model.py
pennprov/models/prov_token_field_model.py
pennprov/models/prov_token_model.py
pennprov/models/prov_token_set_model.py
pennprov/models/qualified_name.py
pennprov/models/qualified_name_attribute.py
pennprov/models/qualified_name_field_model.py
pennprov/models/rank_instance.py
pennprov/models/relation_model.py
pennprov/models/response_error.py
pennprov/models/store_link_model.py
pennprov/models/store_node_model.py
pennprov/models/string_attribute.py
pennprov/models/string_field_model.py
pennprov/models/subgraph_instance.py
pennprov-2.2.11.dist-info/LICENSE.txt
pennprov-2.2.11.dist-info/METADATA
pennprov-2.2.11.dist-info/WHEEL
pennprov-2.2.11.dist-info/top_level.txt
pennprov-2.2.11.dist-info/RECORD
