Metadata-Version: 2.1
Name: pennprov
Version: 2.2.11
Summary: Habitat repository and authorization API
Home-page: https://bitbucket.org/penndb/pennprov
Author: UNKNOWN
Author-email: zives@seas.upenn.edu
License: UNKNOWN
Keywords: Swagger,Habitat repository and authorization API
Platform: UNKNOWN
Requires-Dist: certifi (>=2017.4.17)
Requires-Dist: python-dateutil (>=2.1)
Requires-Dist: six (>=1.10)
Requires-Dist: urllib3 (>=1.23)
Requires-Dist: pandas (>=1.0)
Requires-Dist: cachetools (>=4.1)
